{
		"ultra1" : [
			"Marius", "Agnathio", "Ollonius", "Cato", "Titus", "Agies", "Gaius", "Andrus", "Marcus", "Cassius"
		],
		"ultra2" :[
			"Chronus", "Tarentus", "Dysorius", "Cassus", "Acastian", "Varenus", "Apollon", "Aggennor", "Castus", "Poladrus"
		],
		"if1" :[
			"Lydus", "Darnath", "Lexandro", "Nereus", "Tylaeus", "Vorn", "Tor", "Boreas", "Jago", "Oreas"
		],
		"if2" :[
			"Hagen", "Mirhen", "Garadon", "Lytanus", "Danithor", "Markov", "Mordelei", "Julan", "Darsway", "Lordann"
		],
		"ba1" :[
			"Amareus", "Erasmus", "Rafael", "Morlaeo", "Leonid", "Faustian", "Donatelus", "Raelyn", "Nicodemus", "Furian"
		],
		"ba2" :[
			"Belarius", "Seraphan", "Moriar", "Naneil", "Castivar", "Arteros", "Redolpho", "Lorenso", "Amuto", "Rephas"
		],
		"rg1" :[
			"Aajz", "Kyrin", "Vykus", "Tryris", "Ordias", "Navaer", "Syras", "Aevar", "Reszan", "Vorkyl"
		],
		"rg2" :[
			"Kaed", "Solari", "Solaq", "Qeld", "Korvaedyn", "Vaanes", "Torvaec", "Klayde", "Moradus", "Ordaris"
		],
		"ws1" :[
			"Anagar", "Khajog", "Suberei", "Khoros", "Jaygor", "Seglei", "Jurgah", "Kaljyk", "Kulghu", "Saghari"
		],
		"ws2" :[
			"Gatughan", "Yesuberei", "Ghol", "Jaghol", "Kandakh", "Mologhai", "Ujumm", "Bhangleo", "J'ungah", "Aghulo"
		],
		"ih1" :[
			"Arreven", "Gorrloch", "Shorrgol", "Galorr", "Dorrghun", "Kaagos", "Barrgus", "Ghorrean", "Orros", "Gdolkin"
		],
		"ih2" :[
			"Feirros", "Graevarr", "Bannus", "Lydriik", "Terrek", "Korvaan", "Urloch", "Rauth", "Varrox", "Xeriis"
		],
		"sw1" :[
			"Gunnar", "Ulfrich", "Laars", "Sven", "Wulfgar", "Erik", "Dolf", "Leif", "Olaf", "Torrvald"
		],
		"sw2" :[
			"Ironaxe", "Icefang", "Orksbane", "the Red", "Wyrmslayer", "Thunderhowl", "Stormstrider", "Stoneshield", "Trollbane", "Greymane"
		],
		"sal1" :[
			"Dak'Lyr", "Sho'Tan", "Tsu'gar", "Fugean", "Xavus", "Nubari", "Vorr'n", "Sholta", "Xa'Vor", "Leotrak"
		],
		"sal2" :[
			"K'Gosi", "Dallor", "Jurr", "Mir'Shan", "Shenn", "Ta'Phor", "Rhoshan", "Antanar", "Shal'Dar", "Gar'Dos"
		],
		"da1" :[         
			"Azkarael", "Zakeal", "Rhellion", "Zoreal", "Azathor", "Shoriel", "Nemator", "Ezekial", "Bethor", "Zadakial"
		],
		"da2" :[
			"Zaborial", "Azdallon", "Zachrus", "Astathor", "Seraphus", "Zanthor", "Kaelon", "Namaat", "Soriel", "Belian"
		],
		"grey1" :[
			"Valdar", "Kaladour", "Pelenas", "Anval", "Drystan", "Garran", "Drako", "Caddon", "Arno", "Verdan"
		],
		"grey2" :[
			"Mordrak", "Torvin", "Thule", "Varn", "Ordan", "Gerontas", "Solor", "Cromm", "Kai", "Trevan"
		],
		"cadian" :[
			"Jens", "Karsk", "Hekler", "Reeve", "Pavlo", "Hektor", "Nils", "Thenmann", "Kyser", "Erlen", "Raphe", "Creed", "Lasko", "Ackerman", "Mattias", "Mortens", "Dansk", "Feodor", "Tomas", "Kolson", "Vance", "Pask", "Niems", "Gryf", "Willem", "Sonnen", "Ekhter", "Farestein", "Dekker", "Graf", "Arvans", "Viers", "Kolm", "Bask", "Vesker", "Pavlo"
		],
		"catachan" :[
			"Gunnarsen", "Harker", "Grytt", "'Snake' Vandien", "Greiss", "Stryker", "Storm", "Lance", "'Crazy' Winters", "Cage", "Hammer", "Cobra", "'Hardhead' Jackson", "'Stonefist' Kage", "'Boss' Stransky", "'Bomber' Johnson", "Jacksen", "Marshall", "'Fangs' Lorson", "'Cold-eye' McKay", "Wolf", "'Shiv' Frost", "Brent", "'Ironheart' McKillen", "'Killer' Crowe", "'Wildman' Weiss", "'Ice' Creek", "Dane", "Steeljaw", "Dransky", "'Slim' Hasker", "Mason", "Hawkes", "Axel", "Carver", "Payne"
		],
		"valhallan" :[
			"Vensk", "Skarrsen", "Chernov", "Dushenko", "Rynsk", "Gorska", "Varence", "Nyska", "Putran", "Dorff", "Tyvosk", "Polanski", "Drekoff", "Vorn", "Hapscheldt", "Olof", "Trevinska", "Schonnen", "Kleiss", "Borys", "Ivanek", "Smirnek", "Kuzentsev", "Vasilesnev", "Petravitch", "Skolov", "Fedorev", "Morazev", "Volko", "Lebesnev", "Egoryn", "Pavlek", "Kozlev", "Stepanovicz", "Nikoli", "Orlakev"
		],
		"tallarn" :[
			"Alem", "Hallain", "Laskair", "Nathal", "Altarem", "Mohal", "Dharem", "Hasman", "Sonnam", "Ushmet", "Shadnan", "Asphret", "Ushad", "Tal'hasen", "Ashmyr", "Shashlem", "Haseed", "Ushar", "Raheim", "Dassed", "Sahleim", "Alhret", "Khaleeth", "Eshmet", "Ul'shalem", "Talannar", "Al'phareim", "El'shan", "Khabir", "Khalym", "'Swiftrider'", "'Dunestrider'", "'Hawkseye'", "'Sand Devil'", "'the Mirage'", "'the hunter'"
		],
		"adeptus1" :[
			"Sy-gex", "Tyr", "Dak", "Ar", "Kappic-Schoelendt", "Tyba", "Dorox", "Alb", "Zyto-Neumann", "Xixos", "Kau", "Rho", "Delpha", "Chu", "Ix", "Neng-Pho", "Bheta", "Zhu", "Lho", "Teppa-Nyxos", "Kor", "Dox", "Sek", "Gryphonne-Reductus", "Tov", "Eq", "Mu", "Rhy", "Dos", "Exitor-Dho", "Fel", "Actus", "Xor", "Decima", "Rax", "Kas"
		],
		"adeptus2" :[
			"-511", "-1111", "-XXVII", "-802", "-323/mk12", "-089", "-744", "-VII", "-18.1", "-656", "-IV", "-110", "-0.4343", "-97/mk24", "-XIX", "-7", "-110100", "-3.16", "-961.34254", "-MXV", "-99", "-2918", "-888.88", "-404", "-1010", "-0.44//K", "-745", "-66.75/mk98", "-1/1/2", "-99941", "-83.2", "-575", "-79.09/5", "-668.2", "-1/5", "-666/2"
		],
		"bl1" :[
			"Zekyr", "Dreccor", "Sorvram", "Thallos", "Zagator", "Korthranus", "Drekva", "Thygmor", "Ashrok", "Azmodial"
		],
		"bl2" :[
			"Aximand", "the Vengeful", "Thrice-Cursed", "Korda", "the Black", "Daemonsblade", "Orakar", "Naxos", "the Mad", "Faithslayer"
		],
		"al1" :[
			"Kyphax", "Inigo", "Thkeln", "Sylas", "Armilus", "Sheed", "Eskyrx", "Jaego", "Askelitar", "Alpharius"
		],
		"al2" :[
			"Sheyr", "Dynas", "Hertzor", "Ranko", "(no cypher)", "23-7", "Phors", "the Mad", "Nul", "(no cypher)"
		],
		"ec1" :[
			"Antinius", "Eidelitor", "Ilitoias", "Teloss", "Abdemis", "Fabian", "Julianis", "Abdelis", "Lycon", "Xiander"
		],
		"ec2" :[
			"Sellion", "Thest", "Atonian", "Vessatar", "Bericosian", "Xandassus", "Tresell", "Vastorius", "Kanasiar", "the Perfect"
		],
		"we1" :[
			"Khargos", "Drakh", "Ashkal", "Gharrax", "Khorgor", "Sorkhos", "Aggravax", "Ashkorh", "Larsakh", "Khaen"
		],
		"we2" :[
			"Skullfiend", "the Reaper", "Khorr", "the Butcher", "the Furious", "Slaughterborn", "Foe Ripper", "the Destroyer", "the Hound", "Thaxxos"
		],
		"death1" :[
			"Gurloch", "Suppurax", "Golchor", "Festasmus", "Rancidius", "Mulgh", "Shurgholgh", "Bubox", "Pustus", "Malignus"
		],
		"death2" :[
			"Urghe", "Volghor", "Grulgus", "the Pestilent", "the Reeking", "the Curdled", "Glouch", "Muttermould", "Thrax", "Trudge"
		],
		"thousand1" :[
			"Phosis", "Amonhep", "Basteq", "Apophitar", "Thotek", "Kalophis", "Phael", "Thotmas", "Imhoden", "Ankhu"
		],
		"thousand2" :[
			"T'Kor", "Basth", "Takar", "Kallisar", "Rhan", "P'Tra", "Manahkmor", "Shen", "Apophontar", "H'Kett"
		],
		"asur1" :[
			"Tenrith", "Justune", "Aleerith", "Yrlla", "Aileer", "Caslith", "Tai'shar", "Jair", "Lurith", "Aleera", "Phyllistra", "Myrnoth", "Fyrram", "Ishylla", "Tishriel", "Aydona", "Galánta", "Ylleth", "Giladrea", "Osinell", "Glenoighi", "Ishtá", "Yvraine", "Intrisiel", "Torc", "Anesh", "Kalistri", "Alee", "Altanish", "Gwyth", "Tyrelli", "Kaithe", "Galrethi", "Noithi", "Braesil", "Meari",	"Fachean", "Tarvaril", "Fánai", "Yrmnoch", "Barahir", "Eldrion", "Dis'ar", "Eldos", "Kinshar", "Rhidhal", "Athairnos", "Eärandil,", "Siriolas", "Bahtaam", "Fian", "Eldroth", "Lorinth", "Illisar", "Ealion", "Elronhir", "Tamishar", "Arenal", "Iradil", "Maur", "Requiel", "Lann", "Yrule", "Ra'thar", "Las'hár", "Arision", "Ingfhar", "Senn", "Hal'thar", "Yrion", "Silgar", "Konrith"
		],
		"asur2" :[
			"the Fireheart", "Kyldroth", "Tridehlá", "Who Walks Alone", "of the Flowing Spirits", "Iydoth", "Brylliel", "Biel-rith", "(no second appelation)", "Iyadolath", "Last of the House of the Ayandi", "the Melancholy", "Llacharni ('brightheart')", "the Huntress", "Aryimelli", "Bringer of Azure Death", "Umachuli", "Shelwe-hann ('Song of Enlightenment')", "Serenti ('glory of the setting sun')", "Ullamar", "Dystari ('that which will never shatter')", "Ciaradh", "Iyadari", "Flethál ('Star-pattern of Perfection')", "the Whisper of Death", "Hanndroth ('Quest Eternal')", "Sheersom", "Cegodari ('who laughs at despair')", "Ullathani ('she who walks many paths')", "Corsikanni ('kin to Corsairs')", "Yn Farwolloch ('deadly to her enemies')", "Indomi", "Saim-Ingrelli ('the grace of the striking snake')", "Ysbwrieli ('Starsplinter')", "Morai-fen", "Undomniel", "Son of Coheria", "Finarfin", "Eldrion", "the Unyielding Fire", "Glaermril", "Arronnás", "Gloywach ('the Glow Dragon')", "the Uncompromising", "of the Noble House of Picarothi", "Enbrondil", "Lladronoth", "Bechareth ('spirit on the wind')", "Ceifulgaithann ('wind rider')", "Undroíl", "Caman ('the avenger')", "Tóir", "Scion of Rhidmar", "the Wanderer", "of the Clan Randras", "Llmaea-fen ('born of black suns')", "Rillietar", "Elarique of Alaitoc", "Sydarus Starstrider", "the Implacable", "Ulthos ('speaker of unspeakable truths')", "Sharnál", "the Deathly Eloquent", "Born of Twilight", "of the Tower of Stars", "Shelwe-nin ('Song of the Fading Star')", "the Undaunted", "Rhianthari ('starlight partially obscured by nebula')", "Eldroneth", "Trithjain ('Storm of the Stars')", "the Rising Star", "Bhanlhar ('avenger of the lost clan')"
		],
		"wych1" :[
			"Ariex", "Melikka", "Grendett", "Vaivel", "Bithandrel", "Ingenue", "Demadyne", "Laelanyel", "Excrucia", "Nathra", "Vrexith", "Thyndrella", "Selithrian", "Xela", "Peiythia", "Uless", "Skyshrin", "Anielyn", "Vyrenik", "Khatryx", "Nyssa", "Phyrix", "Mellyx", "Kherissa", "Tryxin", "Aniellah", "Veshtari", "Morghynn", "Thrixxesh", "Thessa", "Xindrell", "Kladys", "Shemriel", "Lyxanna", "Nimhre", "Vylekh"
		],
		"wych2" :[
			"La'flenz", "Wysp", "Soriel", "Oblique", "Nervose", "HektMournor", "Vivicon", "Viserhyx", "Berrebaal", "Vulptuse", "Ehlynna", "Khaur", "Hexehss", "the Crimson", "Thrix", "Khoryssa", "Vexx", "of the Screaming Blade", "Khrygg", "Nichtren", "Veluxis", "the Huntress", "Beastbane", "the Magnificent", "Trehll", "Xyriphraxis", "Masdruvael", "Khrone", "the Untouched", "Bloodslyk", "the Cruel", "Kharavyxis", "Ynthrekh", "Dyvahur", "Krael", "the Bloodsister"
		],
		"kabal1" :[
			"Anarkyss", "Veth'va", "Mayator", "Quacz", "Daisan", "Bekliel", "Orvak", "Narlek", "Monsatos", "Vivithrax", "Drevakh", "Kyzarkh", "Thresyn", "Shylas", "Lythric", "Kylos", "Threskril", "Skythe", "Akkhar", "Kharsac", "Nyktos", "Grevyth", "Thraed", "Sykil", "Khaeyl", "Madrax", "Akhirion", "Vypus", "Ethriliac", "Kheraes", "Iyshak", "Khepres", "Eldoriac", "Vrekkus", "Thayd", "Xurul"
		],
		"kabal2" :[
			"Sar'sel", "Vorpex", "Kreen", "the Bloodbreather", "Maestros", "Gaarsus", "Ehthrek", "Ghorghast", "Ignyss", "Mohrkhar", "Thresk", "Scaur", "the Pale", "Khadylus", "Phrel", "Vulkyriax", "Nul", "the Flenser", "Poisonblade", "Barbtongue", "Xesh", "the Ravening", "Draeven", "of the Obsidian Needle", "Vhrex", "Kaghmyr", "Thrail", "Flickerblade", "Xosh", "the Bleak", "Neverbreath", "Skahyl", "Verkosian", "Ulthurian", "Menesh", "the Cruel"
		],
		"harlequins1" :[
			"The Sun", "The Star", "The Shadow", "The Void", "The Sky", "The Redtide", "The Moon", "The Highborn", "The Leering", "The Bladed"
		],
		"harlequins2" :[
			"King", "Queen", "Prince", "Knave", "Witch", "Judge", "Executioner", "Seer", "Ghoul", "Crone"
		],
		"necron1" :[
			"Ankhep", "Tamonhak", "Eknotath", "Khotek", "Thanatar", "Amhut", "Karok", "Zan-Tep", "Unakh", "Khophec", "Tzantath", "Tahar", "Imonekh", "Trazat", "Xeoptar", "Hamanet", "Oberek", "Banatur", "Ahmnok", "Kophesh", "Teznet", "Odakhar", "Kythok", "Eknothet", "Anubitar", "Anokh", "Thotep", "Anhutek", "Ikhatar", "Thotmek", "Ramatek", "Homanat", "Taknophet", "Makhret", "(no first appellation)", "Zanatek"
		],
		"necron2" :[
			"the Unliving", "the Gilded", "the Great", "the Exalted", "the Loyal", "the Cruel", "the Storm's Eye", "the Bloodied", "the Mighty", "the Relentless", "the Unforgiving", "the Merciless", "the Glorious", "the Devoted", "the Victorious", "the Destroyer", "the Shrouded", "the Flenser", "the Unstoppable", "the Beheader", "the Impaler", "the Magnificent", "the Illuminated", "the Executioner", "the Phaeron's Hand", "the Guardian", "the Gatekeeper", "the All-seeing", "the All-knowing", "the Starkiller", "the Lifetaker", "the Godbreaker", "the Torchbearer", "the Stormbringer", "the Colossus"
		],
		"ork1" :[
			"Urzog", "Snikrat", "Krogskull", "Gorgrok", "Droknog", "Grodd", "Zogwarp", "Gitzog", "Ruggat", "Zargruk", "Stugbrog", "Snarkrat", "Zagblag", "Bokgrobber", "Zarknutz", "Dhakadak", "Nargrunt", "Farksnot", "Gharagh", "Urlakk", "Zogger", "Slazbag", "Squigface", "Ugul", "Tuska", "Nakboz", "Skarzot", "Kroggler", "Grukk", "Fragbad", "Traknug", "Grizgutz", "Shrokbog", "Kraznag", "Gragnatz", "Blokrotz"
		],
		"ork2" :[
			"Drakka", "Grug", "Gitstompa", "Skullcrusha", "Facekrumpa", "the 'Ard", "Grot Kicker", "da Shiv", "(no uvver bit)", "Blaktoof", "da Hammer", "Ghazbhag", "Steelfang", "Daggafist", "Squigbiter", "da Stompy", "da Facegrinda", "Loudgob", "Facebiter", "da Maniak", "Steelbootz", "Ripblade", "'Umiechewa", "Ironboot", "Flame Spitta", "Wurldkilla", "Stompkrumpa", "Spleenrippa", "Bigfangz", "Badfang", "Snotkicka", "Brewguzzla", "Bonesplitta", "'Eadkrakka", "Madeye", "Trakeye"
		],
		"tau" :[
			"Sul'an", "Ho'sen", "Atsumo", "N'ea", "Els'im", "K'yen", "Orbs", "Pashera", "Rais", "Sel'tas", "Be'tol", "E'yaal", "Murakan", "To'jo", "Kurami", "U'so", "Lorresa", "Paluto", "Ren'as", "Lor'ma", "Tash'lor", "Watana", "Nomura", "Nishino", "D'tano", "Xo'yima", "T'suka", "Kais", "Sharmasa", "Pu'jato", "Ju'yem", "Ga'mo", "Kasashi", "Lamano", "Mi'daro", "Uvash'a"
		],
		"tyranid1" :[
			"The Omega", "The Creeping", "The Crimson", "The Kraken's", "The Leviathan's", "The Behemoth's", "Jormungandr's", "The Serpent's", "The Hydra's", "The Rising", "The Devouring", "The Looming", "The Gorgon's", "The Ravening", "The Kolorian", "The Icharian", "The Writhing", "The Inescapable", "The Dark", "Kronos'", "The Nightmare", "Tiamet's", "The Ominous", "Ouroboris'", "The Ancient", "The Slithering", "The Bladed", "The Monstrous", "The Elder", "The Nameless", "The Hunter's", "The Formless", "The Sudden", "The Void", "The Lurking", "The Hungry"
		],
		"tyranid2" :[
			"Infestation", "Talon", "Fang", "Claw", "Tendril", "Coil", "Eye", "Brood", "Shadow", "Dread", "Swarm", "Barb", "Jaws", "Assassins", "Slayers", "Executioners", "Ghosts", "Echo", "Terrors", "Horrors", "Lurkers", "Heralds", "Sting", "Bite", "Doom", "Buchers", "Devils", "Wraiths", "Menace", "Shroud", "Annihilators", "Scream", "Pall", "Devourers", "Stalkers", "Maw"
		],
		"genestealer1" :[
			"Gannar", "Dhraz", "Yohrick", "Kol", "Hastun", "Sayben", "Hollan", "Narek", "Rauss", "Basc", "Davon", "Zask", "Nasser", "Seimon", "Jacobiah", "Skir", "Ghaskin", "Foyle", "Kreen", "Judh", "Mordecai", "Isaak", "Michon", "Jerec", "Aldren", "Madrax", "Vyrion", "Hollun", "Steen", "Pike", "Mallick", "Groust", "Eldric", "Yorl", "Xandus", "Crasker"
		],
		"genestealer2" :[
			"Druchmann", "Kreel", "Desh", "Cavorla", "Krauss", "Gardlinger", "Zorbech", "Stennvar", "Varnway", "Starn", "Baumgart", "Drisso", "Sammer", "Helm", "Tarnright", "Valka", "Kelbrech", "Kheiser", "Madrach", "Venner", "Novek", "Svodnor", "Black", "Barchus", "Matterzhek", "Onderghast", "Thrace", "Lhaska", "Rezzekh", "Carleon", "Drevender", "Seifer", "Vreel", "Xyben", "Gorl", "Arnalt"
		],

		"astartes3" :[
			"Crusaders", "Last Survivors", "Seekers After Vengeance", "Oath Sworn", "Infiltration Specialists", "Hand-picked Heroes", "Tactical Strike Force", "Fire Support", "Honour Guard", "Extermination Force"
		],
		"astartes4" :[
			"Shock and Awe", "Assassination", "Secure and Control", "Hold the Line", "Hit and Run", "Scouting Mission", "Rescue Mission", "Eliminate Target", "Line Breakers", "Speartip"
		],
		"astartes5" :[
			"Stubborn", "Dynamic", "Stealthy", "Zealous", "Exemplars", "Selfless", "Merciless", "Vendetta", "Bloodthirsty", "Strategists"
		],
		"deathwatch3" :[
			"Aquila Kill Team", "Furor Kill Team", "Venator Kill Team", "Dominatus Kill Team", "Malleus Kill Team", "Purgatus Kill Team", "Fortis Kill Team", "Mission Survivors", "The Long Hunt", "The Shield that Slays"
		],
		"deathwatch4" :[
			"Secure and Control", "The Cull", "Cut Off the Head", "Disrupt the Swarm", "The Heart of the Hive", "Knowledge is Power"
		],
		"deathwatch5" :[
			"Newly Forged", "Xenovendetta", "Competitive", "Pragmatic", "Bellicose", "The Bigger Picture"
		],
		"grey3" :[
			"They Hunt the Beast", "Those That Remain", "Purgation Corps", "Sworn Guardians", "Hand of the Prognosticars", "The Heroic Few"
		],
		"grey4" :[
			"End the Nightmare", "Aquisitus Prohibitum", "Wield the True Name", "Reap the Tally", "Scorched Earth", "Trial by Blade"
		],
		"grey5" :[
			"Unyielding", "Blessed Aura", "Exacting", "Bellicose", "Sworn to Purify", "Dark Lore"
		],
		"astra3" :[
			"Penal Troopers", "Hardened Veterans", "Light Infantry", "Sappers", "Elite Guards", "Fresh Meat", "Drop Troops", "Tank Hunters", "Shock Troops", "Grizzled Survivors"
		],
		"astra4" :[
			"Hold at All Costs", "Assault", "Assassinate", "Demolitions", "Die Well", "Raiders", "Capture Location", "Recon", "Messengers", "Looters"
		],
		"astra5" :[
			"Faithful", "Parade Ground Drilled", "Tunnel Fighters", "City Fighters", "Death Worlders", "Xenos Hunters", "Seen Too Much", "Chem-addicts", "Gone Native", "Killer Rep"
		],
		"adeptus3" :[
			"Explorator Team", "Archeotech Hunters", "Elimination Clade", "Campaign Veterans", "Titan Guards", "Rad-zone Corps", "Infiltrator Clade", "Domination Cadre", "Itratii Cadre", "Corpus-Sactarii Clade"
		],
		"adeptus4" :[
			"Defend the Sacred Technologies", "Recover a Holy Prize", "Biologis Sample Extraction", "Strategic Martyrdom", "Smite a Tech-heretic", "Eliminate Heretical Machineries", "Righteous Auto-castigation", "Root Out Techno-dissidents", "Eradicate False Testament", "Victory for Logic"
		],
		"adeptus5" :[
			"Acquisitive", "Jealous Guardians", "Mindlessly Devout", "Requiring Re-sanctification", "Monotask", "Pursuing Auto-perfection", "Cybernetic Ascension", "Mercilessly Decisive", "Secretive", "Beyond the Crux Mechanicus"
		],
		"heretic3" :[
			"Champions All", "Lost and Damned", "Veterans of the Long War", "Predators", "Warp-infused Warriors", "Tzeentch Worshippers", "Khorne Worshippers", "Slaanesh Worshippers", "Nurgle Worshippers", "Worldslayers"
		],
		"heretic4" :[
			"Terror Raid", "Seed Corruption", "Dark Ritual", "Sunder the Gates", "Arcane Prize", "Faithbreakers", "Seekers After Glory", "Hand of the Gods", "Dark Guardians", "Saboteurs"
		],
		"heretic5" :[
			"Embittered", "Berserk", "Devious", "Zealous", "Cruel", "Stolid", "Iron Discipline", "Arrogant", "Insane", "Possessed"
		],
		"death3" :[
			"The Virulent", "Dark Alchemists", "Trench Fighters", "Mortarion's Chosen", "Reapers", "Shepherds of the Neverdead"
		],
		"death4" :[
			"Defilers", "Seize and Profane", "Victory Through Endurance", "Sevenfold Slaughter", "Fatal Infection", "Warp-spores"
		],
		"death5" :[
			"Morbid Mirth", "Justifiable Arrogance", "Dirgesong", "Vengeful", "Servants of Entropy", "Relentless"
		],
		"thousand3" :[
			"Heralds of Madness", "Seekers After Sorcery", "Arch-coven", "Relentless Destroyers", "Warriors Out of Time", "Daemonologists"
		],
		"thousand4" :[
			"Ritual Desecration", "Abduction", "Sowing Sorcery", "Firestorm", "Vengeance for Prospero", "Hands of Fate"
		],
		"thousand5" :[
			"Aetheric Coronae", "One Will", "Single-Minded", "Ancient Dust", "Superior", "Ghosts of the Warp"
		],
		"asur3" :[
			"Gwynt'ar Fue", "Pre-emptive Strike", "Keepers of the Gate", "The Shrine Ascendant", "Shadow Squad", "Echoes of Greatness", "Ily'Haeth Khai", "Cleansers", "The Bladed Mirror", "Wardens of the Pivotal Life"
		],
		"asur4" :[
			"Enact the Bailic-fen", "Suprise Attack", "Keepers of the Gate", "Talons of Heg", "Fate's Executioners", "Forbidden Ground", "The First Wave", "Faolchú's Wings", "A greater Foe", "Mobile Defence", "Phyllistra", "Myrnoth", "Fyrram", "Ishylla", "Tishriel", "Aydona", "Galánta", "Ylleth", "Giladrea", "Osinell", "Glenoighi", "Ishtá", "Yvraine", "Intrisiel", "Torc", "Anesh", "Kalistri", "Alee", "Altanish", "Gwyth", "Tyrelli", "Kaithe", "Galrethi", "Noithi", "Braesil", "Meari",	"Fachean", "Tarvaril", "Fánai", "Yrmnoch", "Barahir", "Eldrion", "Dis'ar", "Eldos", "Kinshar", "Rhidhal", "Athairnos", "Eärandil,", "Siriolas", "Bahtaam", "Fian", "Eldroth", "Lorinth", "Illisar", "Ealion", "Elronhir", "Tamishar", "Arenal", "Iradil", "Maur", "Requiel", "Lann", "Yrule", "Ra'thar", "Las'hár", "Arision", "Ingfhar", "Senn", "Hal'thar", "Yrion", "Silgar", "Konrith"
		],
		"asur5" :[
			"Close Bonds", "Fickle", "Merciless Hate", "Sorrows Beyond Measure", "Psychically Attuned", "Uncanny Perfectionists", "Servants of Prophecy", "Superior", "A Shining Example", "Arrogant and Aloof"
		],
		"druk3" :[
			"Vanguard Party", "Slave Trialists", "Ascendant Murderers", "Enemies of My Enemy", "Avatars of the Arenas", "Slithering Compulsion", "Hired Blades", "Betrayers", "One Shall Stand", "Desolators"
		],
		"druk4" :[
			"Probe", "Harvest", "Interrogate", "Assassinate", "Deceive", "Terrorize", "Abduct", "Enslave", "Disembowel", "Revel"
		],
		"druk5" :[
			"Sinful Focus", "Revel in Pain", "Swift and Deadly", "Reckless", "Territorial", "Trophy Hunters", "Eldritch Cunning", "Masochistic", "Shadow Stalkers", "Consummate Provocateurs"
		],
		"harlequins3" :[
			"The Swords of Khaine", "Webway Wanderers", "The Solitary", "Fate's Messengers", "Sinister Killers", "Guardians of the Black Library"
		],
		"harlequins4" :[
			"The Dance of the Thief's Reward", "The Dance of Kurnous' Gate", "The Dance of the Crimson Reaping", "The Dance of the Veiled Blade", "The Dance of the Starving Ygghs", "The Dance of Vaul's Tempering"
		],
		"harlequins5" :[
			"Warriors of the Light", "Blades of the Twilight", "Talons of the Dark", "Swift as the Wind", "Cruelly Mocking", "Starlight Stride"
		],
		"necron3" :[
			"Harbingers", "Tomb Guardians", "Invaders from Beyond", "The Phaeron's Chosen", "Scouring Party", "Code-bound", "Assassins", "Ghoulish Nightmares", "Mindless Martyrs", "Domination Force"
		],
		"necron4" :[
			"The Cull", "Mindthieves", "Servants of the Crypteks", "Heralds of the Uprising", "Chrono-aquisitors", "Fractal Disruption", "Punishment Detail", "Relentless War", "The Phaeron's Blade", "The Phaeron's Curse"
		],
		"necron5" :[
			"The Curse of Time", "Wreathed in Power", "Deadly Automata", "Dark Sentience", "Ether-flux", "Skin-takers", "Arrogant Hunters", "Deranged", "Unfeeling", "Favoured Warriors"
		],
		"ork3" :[
			"Gung-ho!", "Filled with Waaagh!", "Skraphuntaz", "The Shootiest", "Sneaky Gits!", "Brutal", "Kunnin'", "Internal Rivalries", "Addicted to Destruction", "Spreaders of the Waaagh!"
		],
		"ork4" :[
			"Kill Their Bosses", "Get Stuck In", "Salvage", "'Andz off", "We'll Show 'Em", "Da Ambush", "Speed Is Its Own Reward", "Sneak About", "Fist of Gork (or Mork)", "Plant da Flag"
		],
		"ork5" :[
			"Loud and Tuneless", "Boastful", "Itchy", "Madboyz", "Krumpin' Krew", "Hard-bitten", "Lucky Gitz", "Pyromaniacs", "Buzzsquigs", "Praktical Jokers"
		],
		"tau3" :[
			"Survivors", "Stealth Experts", "Prototype Weapons Testers", "Edification Team", "Urban Combat Specialists", "Heroes of the Greater Good", "Bodyguard Retinue", "Elite of the Academics", "Fourth Sphere Veterans", "Sniper Team"
		],
		"tau4" :[
			"Bait the Trap", "Mark the Target", "Destroy the Enemy Supplies", "Assassination", "Ambush", "Extract the Target", "Weapons Test", "Seize Vital Intel", "Forward Reconnaissance", "Defend Strategic Asset"
		],
		"tau5" :[
			"Honourable Warriors", "Vengeful", "Unyielding", "Students of Kauyon", "Students of Mont'ka", "Canny Tacticians", "No Heroes", "Tech-minded", "Ghosts", "No One Left Behind"
		],
		"tyranid3" :[
			"Stealth Brood", "Devourer Brood", "Swiftkiller Brood", "Highcrawler Brood", "Bombardment Brood", "Kill-swarm", "Living Barricade", "Alpha Pack", "Ambush Brood", "Kinglsayer Brood"
		],
		"tyranid4" :[
			"Devour", "Infiltrate", "Cull", "Swarm", "Terrify", "Rampage", "Stalk", "Spread", "Protect", "Shroud"
		],
		"tyranid5" :[
			"Ravenous", "Cautious", "Slinking", "Bladed Shoal", "Inescapable Hunters", "Shrieker Blood", "Sizzling Gore", "Heightened Senses", "Shorn of Synapse", "Catalysed"
		],
		"genestealer3" :[
			"Scavenger Cell", "The Prophet's Claw", "Tunnel Skulkers", "Killers in the Fold", "Eyes of the Patriarch", "Iconoclast Cell", "Snatcher Cell", "Shadowstalker Gene-kin", "Snare Setters", "Veterans of the First Cycle"
		],
		"genestealer4" :[
			"Open Their Eyes", "Feed the Progeny", "Raid Supply Lines", "Prepare the Killing Field", "Sabotage Vital Machinery", "Undertunnel Ambush", "They Know Too Much", "Spread the Cult", "Tear Down False Idols", "From Below"
		],
		"genestealer5" :[
			"Deep-dwellers", "Gene-kin Cant", "Rabid Evangelists", "Anarchists", "Devious Scum", "Twisted Physiologies", "Fanatics", "Creeping Killers", "Inhuman Cruelty", "Murderous"
		],
		"astartes6" :[
			"Dour", "Ebullient", "Aggressive", "Castellan", "Noble", "Xenophobic", "Ferocious", "Sombre", "Mysterious", "Charismatic"
		],
		"deathwatch6" :[
			"Newcomer", "Black Shield", "Xenobiologist", "Fuelled by Hate", "Tactician", "Huntsman", "Marksman", "Grim", "Contemptuous", "Murderous"
		],
		"grey6" :[
			"Wrathful", "Fanatical", "Mystic", "Methodical", "Firebrand", "Vengeful", "Marksman", "Psychic Nexus", "Merciless", "Stoic"
		],
		"astra6" :[
			"Dutiful", "Haunted", "Nerves of Steel", "Pious", "Eagle-eye", "Courageous", "Vengeful", "Psycho", "Expert", "Gung-ho"
		],
		"adeptus6" :[
			"Meticulously Observant", "Binharic Piety", "Biologis Cognis", "Mechadominus", "Defensor Majoris", "Memeglitch", "Uncompromator Doctrines", "Ironstride", "Strategic Chorister", "Autopuritanical Ballistics"
		],
		"heretic6" :[
			"Ultimate Veteran", "Cannibal", "Deranged", "Blade-master", "Visionary", "Living Canker", "Unstoppable Force", "Twisted", "True Believer", "On the Brink"
		],
		"death6" :[
			"Drudge", "Morbid Fascinations", "Jocular", "Generous", "Belligerent", "Meticulous", "Deathflinger", "Reeking Horror", "Taking Samples", "Stubborn"
		],
		"thousand6" :[
			"Enigmatic", "Exacting", "Ninefold Warrior", "War is an Altar", "The Madness of Tzeentch", "Unspeaking", "Plans Within Plans", "Prophesier", "Pyromaniac", "Seething with Change"
		],
		"asur6" :[
			"Acrobatic", "Mentally Dextrous", "Crystalline Soul", "Damned", "Survivor's Guilt", "Absolute Focus", "Haughty", "Cold as the Void", "Passionate", "Grandiloquent"
		],
		"druk6" :[
			"Predator's Eye", "Dark Flamboyance", "Ravenous", "Extravagant", "Scheming", "Mistrustful", "Darkened Soul", "Unforgiving", "Boundless Ambition", "Vindictive"
		],
		"harlequins6" :[
			"Heroic Protagonist", "Malicious Antagonist", "Bladed Fool", "Sorrowful Killer", "Gleeful Maniac", "Relentless Destroyer", "Sombre Executioner", "Fate's Herald", "Eternal Wanderer", "The Harmonious Herald"
		],
		"necron6" :[
			"Menacing", "Maniacal", "Strategic", "Nihilist", "Tormentor", "Glitching", "Obsessive", "Delusional", "Acquisitive", "Necrochirurgeon"
		],
		"ork6" :[
			"Thick-headed", "Heavily Scarred", "Stubborn", "Light-fingered", "Violent Loon", "Resilient", "Beady-eyed", "Too Dumb to Know Fear", "Foul Gob", "Big and Brawny"
		],
		"tau6" :[
			"Scholar of Puretide", "Pragmatic", "Precise", "Hot-Blooded", "Wise Veteran", "Unflappable", "Perceptice", "Dishonoured", "Farsight Sympathiser", "Monat"
		],
		"tyranid6" :[
			"Hive Node", "Sentient Ammunition", "Entangling Tendrils", "Synaptophage", "Guardian Beast", "Survival Instincts", "Bloodhunger", "Unsettling Presence", "Lurker", "Mimic"
		],
		"genestealer6" :[
			"Acidic Spittle", "Strange Twitching", "Enlightener", "Marker of the Dead", "Unblinking", "Proselytiser", "Tunnelspawn", "Destined Ascension", "Predatory Instincts", "Born Survivor"
		]
}